{"metrics.box.map50": {"value": 0.9936268232700521, "description": "Mean Average Precision at IoU threshold of 0.5 for all classes."}, "metrics.box.map75": {"value": 0.988703662995346, "description": "Mean Average Precision at IoU threshold of 0.75 for all classes."}, "metrics.box.ap": {"value": 0.9024533375358468, "description": "Average Precision at IoU thresholds from 0.5 to 0.95 for all classes."}, "metrics.box.mp": {"value": 0.9927093316382087, "description": "Mean Precision of all classes."}, "metrics.box.mr": {"value": 0.9933130699088146, "description": "Mean Recall of all classes."}, "metrics.box.p": {"value": 0.9927093316382087, "description": "Precision for each class."}, "metrics.box.r": {"value": 0.9933130699088146, "description": "Recall for each class."}, "metrics.box.f1": {"value": 0.9930111090072005, "description": "F1 score for each class."}, "metrics.box.nc": {"value": 1, "description": "Number of classes."}}